setup.cfg
setup.py
./__init__.py
./beanstream_api.py
./transaction.py
./transaction.xml
./tryton.cfg
./tests/__init__.py
./tests/test_transaction.py
./tests/test_view_depends.py
./view/gateway_form.xml
./view/transaction_form.xml
./view/transaction_list.xml
openlabs_payment_gateway_beanstream.egg-info/PKG-INFO
openlabs_payment_gateway_beanstream.egg-info/SOURCES.txt
openlabs_payment_gateway_beanstream.egg-info/dependency_links.txt
openlabs_payment_gateway_beanstream.egg-info/entry_points.txt
openlabs_payment_gateway_beanstream.egg-info/not-zip-safe
openlabs_payment_gateway_beanstream.egg-info/requires.txt
openlabs_payment_gateway_beanstream.egg-info/top_level.txt